hdp/__init__.py
hdp/cli.py
hdp/definitions.py
hdp/measure.py
hdp/metric.py
hdp/pacl.mplstyle
hdp/threshold.py
hdp/utils.py
hdp/graphics/__init__.py
hdp/graphics/figure.py
hdp/graphics/hdp.mplstyle
hdp/graphics/notebook.py
hdp/graphics/winkel_tripel.py
hdp/tests/__init__.py
hdp/tests/test_heatwave_average.py
hdp/tests/test_heatwave_duration.py
hdp/tests/test_heatwave_frequency.py
hdp/tests/test_heatwave_number.py
hdp/tests/test_index_heatwaves.py
hdp/tests/test_utils.py
hdp/tests/test_workflow.py
hdp_python-1.0.2.dist-info/licenses/LICENSE
hdp_python-1.0.2.dist-info/METADATA
hdp_python-1.0.2.dist-info/WHEEL
hdp_python-1.0.2.dist-info/entry_points.txt
hdp_python-1.0.2.dist-info/top_level.txt
hdp_python-1.0.2.dist-info/RECORD
