Metadata-Version: 2.4
Name: HDP_python
Version: 1.0.2
Summary: Heatwave Diagnostics Package (HDP) for computing heatwave metrics over gridded timeseries data.
Author-email: Cameron Cummins <cameron.cummins@utexas.edu>
License: MIT License
Project-URL: Homepage, https://github.com/AgentOxygen/HDP
Project-URL: Issues, https://github.com/AgentOxygen/HDP
Keywords: HDP,heat,heatwave,heatwave diagnostics package,climate,climate model,timeseries,heatwave metrics,diagnostics
Classifier: Programming Language :: Python :: 3
Classifier: License :: OSI Approved :: MIT License
Classifier: Operating System :: OS Independent
Requires-Python: >=3.12.3
License-File: LICENSE
Requires-Dist: numpy
Requires-Dist: xarray>=2025.1.1
Requires-Dist: cartopy
Requires-Dist: numba>=0.60.0
Requires-Dist: nc_time_axis
Requires-Dist: dask[complete]
Requires-Dist: zarr
Requires-Dist: netCDF4
Requires-Dist: tqdm
Requires-Dist: ipywidgets
Requires-Dist: nbformat
Dynamic: license-file
